docs/Makefile
docs/__init__.py
docs/authors.rst
docs/conf.py
docs/contributing.rst
docs/history.rst
docs/index.rst
docs/installation.rst
docs/make.bat
docs/readme.rst
docs/usage.rst
example/__init__.py
example/manage.py
example/example/__init__.py
example/example/settings.py
example/example/urls.py
example/example/wsgi.py
example/rebotics_sdk_receiver/__init__.py
example/rebotics_sdk_receiver/admin.py
example/rebotics_sdk_receiver/apps.py
example/rebotics_sdk_receiver/models.py
example/rebotics_sdk_receiver/signals.py
example/rebotics_sdk_receiver/tests.py
example/rebotics_sdk_receiver/views.py
example/rebotics_sdk_receiver/migrations/__init__.py
rebotics_sdk/__init__.py
rebotics_sdk/constants.py
rebotics_sdk/utils.py
rebotics_sdk/advanced/__init__.py
rebotics_sdk/advanced/flows.py
rebotics_sdk/advanced/packers.py
rebotics_sdk/advanced/remote_loaders.py
rebotics_sdk/advanced/reverse_planogram.py
rebotics_sdk/cli/__init__.py
rebotics_sdk/cli/admin.py
rebotics_sdk/cli/authenticated_provider.py
rebotics_sdk/cli/common.py
rebotics_sdk/cli/dataset.py
rebotics_sdk/cli/draw.py
rebotics_sdk/cli/fvm.py
rebotics_sdk/cli/hawkeye.py
rebotics_sdk/cli/renderers.py
rebotics_sdk/cli/retailer.py
rebotics_sdk/cli/tasks.py
rebotics_sdk/cli/utils/__init__.py
rebotics_sdk/cli/utils/base.py
rebotics_sdk/cli/utils/configurations.py
rebotics_sdk/cli/utils/contexts.py
rebotics_sdk/hook/__init__.py
rebotics_sdk/hook/apps.py
rebotics_sdk/hook/serializers.py
rebotics_sdk/hook/settings.py
rebotics_sdk/hook/signals.py
rebotics_sdk/hook/urls.py
rebotics_sdk/hook/views.py
rebotics_sdk/hook/migrations/__init__.py
rebotics_sdk/hook/tests/__init__.py
rebotics_sdk/hook/tests/test_emitter_signal.py
rebotics_sdk/providers/__init__.py
rebotics_sdk/providers/admin.py
rebotics_sdk/providers/base.py
rebotics_sdk/providers/cvat.py
rebotics_sdk/providers/dataset.py
rebotics_sdk/providers/fvm.py
rebotics_sdk/providers/hawkeye.py
rebotics_sdk/providers/retailer.py
rebotics_sdk/providers/utils.py
rebotics_sdk-0.31.1.dist-info/licenses/AUTHORS.rst
rebotics_sdk-0.31.1.dist-info/METADATA
rebotics_sdk-0.31.1.dist-info/WHEEL
rebotics_sdk-0.31.1.dist-info/entry_points.txt
rebotics_sdk-0.31.1.dist-info/top_level.txt
rebotics_sdk-0.31.1.dist-info/RECORD
