Metadata-Version: 2.4
Name: rebotics_sdk
Version: 0.31.1
Summary: API client and CLI tools for working with SymphonyAI Store Intelligence platform
Home-page: http://retechlabs.com/rebotics/
Author: Malik Sulaimanov
Author-email: malik.sulaimanov@symphonyai.com
Keywords: rebotics_sdk
Classifier: Development Status :: 5 - Production/Stable
Classifier: Intended Audience :: Developers
Classifier: Natural Language :: English
Classifier: Programming Language :: Python :: 3.7
Classifier: Programming Language :: Python :: 3.8
Classifier: Programming Language :: Python :: 3.9
Classifier: Programming Language :: Python :: 3.10
Classifier: Programming Language :: Python :: 3.11
Classifier: Programming Language :: Python :: 3.12
License-File: AUTHORS.rst
Requires-Dist: requests
Requires-Dist: dataclasses; python_version < "3.7"
Requires-Dist: more-itertools
Requires-Dist: tqdm
Requires-Dist: chardet
Requires-Dist: py7zr<1.0.0
Requires-Dist: pydantic
Provides-Extra: hook
Requires-Dist: django; extra == "hook"
Requires-Dist: djangorestframework; extra == "hook"
Provides-Extra: shell
Requires-Dist: ipython; extra == "shell"
Requires-Dist: pandas; extra == "shell"
Requires-Dist: pytz; extra == "shell"
Requires-Dist: ptable; extra == "shell"
Requires-Dist: python-dateutil; extra == "shell"
Requires-Dist: humanize; extra == "shell"
Requires-Dist: click>8.0; extra == "shell"
Requires-Dist: pyyaml; extra == "shell"
Requires-Dist: requests-toolbelt; extra == "shell"
Requires-Dist: requests-to-curl==1.1.0; extra == "shell"
Provides-Extra: async
Requires-Dist: httpx>=0.24.0; extra == "async"
Provides-Extra: test
Requires-Dist: pytest; extra == "test"
Requires-Dist: requests-mock; extra == "test"
Requires-Dist: pytest-mock; extra == "test"
Requires-Dist: pytest-cov; extra == "test"
Requires-Dist: pytest-runner; extra == "test"
Provides-Extra: all
Requires-Dist: python-dateutil; extra == "all"
Requires-Dist: pyyaml; extra == "all"
Requires-Dist: requests-to-curl==1.1.0; extra == "all"
Requires-Dist: httpx>=0.24.0; extra == "all"
Requires-Dist: pytest; extra == "all"
Requires-Dist: requests-toolbelt; extra == "all"
Requires-Dist: requests-mock; extra == "all"
Requires-Dist: pytest-cov; extra == "all"
Requires-Dist: django; extra == "all"
Requires-Dist: pytest-mock; extra == "all"
Requires-Dist: humanize; extra == "all"
Requires-Dist: pytest-runner; extra == "all"
Requires-Dist: ipython; extra == "all"
Requires-Dist: pandas; extra == "all"
Requires-Dist: pytz; extra == "all"
Requires-Dist: djangorestframework; extra == "all"
Requires-Dist: ptable; extra == "all"
Requires-Dist: click>8.0; extra == "all"
Dynamic: author
Dynamic: author-email
Dynamic: classifier
Dynamic: description
Dynamic: home-page
Dynamic: keywords
Dynamic: license-file
Dynamic: provides-extra
Dynamic: requires-dist
Dynamic: summary
